thumb/__init__.py
thumb/ape.py
thumb/app.py
thumb/core.py
thumb/llm.py
thumb/utils.py
thumb-0.2.9.dist-info/METADATA
thumb-0.2.9.dist-info/WHEEL
thumb-0.2.9.dist-info/top_level.txt
thumb-0.2.9.dist-info/RECORD
