Metadata-Version: 2.1
Name: thumb
Version: 0.2.9
Summary: A simple prompt testing library for LLMs.
Home-page: https://github.com/hammer-mt/thumb
Author: Mike Taylor
Author-email: mike@saxifrage.xyz
License: MIT
Requires-Dist: gradio
Requires-Dist: langchain
Requires-Dist: ipython
Requires-Dist: ipywidgets
Requires-Dist: openai
Requires-Dist: tqdm
